{
  "editor:toggle-fold-properties": [
    {
      "modifiers": [
        "Alt",
        "Mod"
      ],
      "key": ";"
    }
  ],
  "editor:delete-paragraph": [],
  "app:toggle-left-sidebar": [
    {
      "modifiers": [
        "Alt",
        "Ctrl",
        "Mod"
      ],
      "key": "ArrowLeft"
    }
  ],
  "app:toggle-right-sidebar": [
    {
      "modifiers": [
        "Alt",
        "Ctrl",
        "Mod"
      ],
      "key": "ArrowRight"
    }
  ],
  "editor:save-file": [],
  "editor:toggle-source": [
    {
      "modifiers": [
        "Mod"
      ],
      "key": "S"
    }
  ],
  "daily-notes": [
    {
      "modifiers": [
        "Mod",
        "Shift"
      ],
      "key": "1"
    }
  ],
  "workspace:new-tab": [
    {
      "modifiers": [
        "Mod"
      ],
      "key": "T"
    }
  ],
  "insert-current-time": [
    {
      "modifiers": [
        "Alt",
        "Mod"
      ],
      "key": "T"
    }
  ],
  "insert-current-date": [
    {
      "modifiers": [
        "Alt",
        "Mod"
      ],
      "key": "W"
    }
  ],
  "app:go-back": [
    {
      "modifiers": [
        "Alt",
        "Mod"
      ],
      "key": "ArrowLeft"
    }
  ],
  "app:go-forward": [
    {
      "modifiers": [
        "Alt",
        "Mod"
      ],
      "key": "ArrowRight"
    }
  ],
  "editor:toggle-blockquote": [
    {
      "modifiers": [
        "Mod"
      ],
      "key": "Q"
    }
  ],
  "obsidian-hider:toggle-tab-containers": [
    {
      "modifiers": [
        "Alt",
        "Shift"
      ],
      "key": "/"
    }
  ],
  "editor:set-heading-5": [
    {
      "modifiers": [
        "Alt"
      ],
      "key": "5"
    }
  ],
  "editor:set-heading-6": [
    {
      "modifiers": [
        "Alt"
      ],
      "key": "6"
    }
  ],
  "editor:set-heading-4": [
    {
      "modifiers": [
        "Alt"
      ],
      "key": "4"
    }
  ],
  "editor:set-heading-3": [
    {
      "modifiers": [
        "Alt"
      ],
      "key": "3"
    }
  ],
  "editor:set-heading-2": [
    {
      "modifiers": [
        "Alt"
      ],
      "key": "2"
    }
  ],
  "editor:set-heading-1": [
    {
      "modifiers": [
        "Alt"
      ],
      "key": "1"
    }
  ],
  "editor:set-heading": [
    {
      "modifiers": [
        "Alt"
      ],
      "key": "0"
    }
  ],
  "editor:toggle-strikethrough": [
    {
      "modifiers": [
        "Alt",
        "Shift"
      ],
      "key": "S"
    }
  ]
}